ad_rss/__init__.py
ad_rss/ad_rss_python311.so
ad_rss.libs/libad_physics-25c66a14.so
ad_rss.libs/libad_rss-5e08bffe.so
ad_rss.libs/libboost_python311-6873131e.so.1.83.0
ad_rss.libs/libfmt-d463bedd.so.8.1.1
ad_rss.libs/libspdlog-1de96ba8.so.1.9.2
ad_rss-5.0.0.dist-info/METADATA
ad_rss-5.0.0.dist-info/WHEEL
ad_rss-5.0.0.dist-info/top_level.txt
ad_rss-5.0.0.dist-info/RECORD
