Metadata-Version: 2.4
Name: ad-rss
Version: 5.0.0
Summary: python binding of the C++ Library implementation of the Responsibility Sensitive Safety model
Home-page: https://intel.github.io/ad-rss-lib/
Author: Intel Corporation
Author-email: bernd.gassmann@intel.com
License: LGPL-2.1-only
Platform: manylinux_2_35_x86_64
Classifier: Programming Language :: Python :: 3
Requires-Dist: ad_physics>=3.0.0
Dynamic: author
Dynamic: author-email
Dynamic: classifier
Dynamic: description
Dynamic: description-content-type
Dynamic: home-page
Dynamic: license
Dynamic: platform
Dynamic: requires-dist
Dynamic: summary
